supamodel/__init__.py
supamodel/supamodel.py
supamodel_py-0.1.2.dist-info/LICENCE
supamodel_py-0.1.2.dist-info/METADATA
supamodel_py-0.1.2.dist-info/WHEEL
supamodel_py-0.1.2.dist-info/entry_points.txt
supamodel_py-0.1.2.dist-info/top_level.txt
supamodel_py-0.1.2.dist-info/RECORD
