Metadata-Version: 2.1
Name: supamodel-py
Version: 0.1.2
Summary: A tool for MLEs to monitor and control experiments from mobile phones
Home-page: https://github.com/sarangzambare/supamodel-py
Author: Sarang Zambare
Author-email: sarang.zambare@gmail.com
Classifier: Programming Language :: Python :: 3
Classifier: License :: OSI Approved :: MIT License
Classifier: Operating System :: OS Independent
Requires-Python: >=3.6
License-File: LICENCE
Requires-Dist: requests
